psyflow_mcp/__init__.py
psyflow_mcp/main.py
psyflow_mcp-0.1.12.dist-info/licenses/LICENSE
psyflow_mcp-0.1.12.dist-info/METADATA
psyflow_mcp-0.1.12.dist-info/WHEEL
psyflow_mcp-0.1.12.dist-info/entry_points.txt
psyflow_mcp-0.1.12.dist-info/top_level.txt
psyflow_mcp-0.1.12.dist-info/RECORD
