Metadata-Version: 2.4
Name: psyflow-mcp
Version: 0.1.12
Summary: A minimal complete project (MCP) for psyflow
Author-email: Zhipeng Cao <zhipeng30@foxmail.com>
License-Expression: MIT
Project-URL: Homepage, https://github.com/TaskBeacon/psyflow-mcp
Project-URL: Repository, https://github.com/TaskBeacon/psyflow-mcp
Project-URL: Bug Tracker, https://github.com/TaskBeacon/psyflow-mcp/issues
Keywords: psyflow,mcp,uv
Classifier: Programming Language :: Python :: 3
Classifier: Operating System :: OS Independent
Requires-Python: >=3.10
License-File: LICENSE
Requires-Dist: httpx
Requires-Dist: GitPython
Requires-Dist: mcp[cli]
Requires-Dist: ruamel.yaml
Requires-Dist: edge_tts
Dynamic: license-file
